aiowhatsapp/__init__.py
aiowhatsapp/context.py
aiowhatsapp/dispatcher.py
aiowhatsapp/handlers.py
aiowhatsapp/markup.py
aiowhatsapp/message.py
aiowhatsapp/whatsapp.py
aiowhatsapp-1.1.0.dist-info/LICENSE
aiowhatsapp-1.1.0.dist-info/METADATA
aiowhatsapp-1.1.0.dist-info/WHEEL
aiowhatsapp-1.1.0.dist-info/RECORD
