Metadata-Version: 2.1
Name: aiowhatsapp
Version: 1.1.0
Summary: A whatsapp client library for python using the new WhatsApp cloud API by Facebook
License: MIT
Author: Solomon Olatunji
Requires-Python: >=3.9,<4.0
Classifier: License :: OSI Approved :: MIT License
Classifier: Operating System :: OS Independent
Classifier: Programming Language :: Python :: 3
Classifier: Programming Language :: Python :: 3.9
Classifier: Programming Language :: Python :: 3.10
Classifier: Programming Language :: Python :: 3.11
Classifier: Programming Language :: Python :: 3.12
Requires-Dist: aiosignal (>=1.3.1,<2.0.0)
Requires-Dist: asyncio (>=3.4.3,<4.0.0)
Requires-Dist: requests (>=2.31.0,<3.0.0)
